MANIFEST.in
setup.py
koboriakira_translate_bookmark.egg-info/PKG-INFO
koboriakira_translate_bookmark.egg-info/SOURCES.txt
koboriakira_translate_bookmark.egg-info/dependency_links.txt
koboriakira_translate_bookmark.egg-info/entry_points.txt
koboriakira_translate_bookmark.egg-info/requires.txt
koboriakira_translate_bookmark.egg-info/top_level.txt
tests/__init__.py
tests/test_article.py
tests/test_url.py
translate_bookmark/__init__.py
translate_bookmark/analyse.py
translate_bookmark/article.py
translate_bookmark/config.py
translate_bookmark/main.py
translate_bookmark/translate_bookmark.py
translate_bookmark/url.py
translate_bookmark/writer.py