Metadata-Version: 1.0
Name: koboriakira-translate-bookmark
Version: 1.4
Summary: 自分がよくみるサイトの翻訳手助けツール
Home-page: https://github.com/koboriakira/koboriakira-translate-bookmark
Author: Kobori Akira
Author-email: private.beats@gmail.com
License: UNKNOWN
Platform: UNKNOWN
